regex_sampler-0.1.4.dist-info/METADATA
regex_sampler-0.1.4.dist-info/WHEEL
regex_sampler/logit_processor.py
regex_sampler/__init__.py
regex_sampler/regex_sampler.abi3.so
regex_sampler-0.1.4.dist-info/RECORD
