Metadata-Version: 2.3
Name: regex_sampler
Version: 0.1.4
Classifier: Programming Language :: Rust
Classifier: Programming Language :: Python :: Implementation :: CPython
Classifier: Programming Language :: Python :: Implementation :: PyPy
Requires-Dist: transformers
Requires-Dist: torch
Requires-Dist: pytest ; extra == 'tests'
Provides-Extra: tests
Requires-Python: >=3.8
